{"name":"makeovermonday_2019w6","title":"2019/W6: How Chinese New Year Compares With Thanksgiving","description":"How Chinese New Year Compares With Thanksgiving\n\n# **Original Visualization**\n![supporting image or chart](https://infographic.statista.com/normal/chartoftheday_3246_How_Chinese_New_Year_Compares_With_Thanksgiving_n.jpg)\n\n# **About this Dataset**\nSOURCE: [Statista](https://www.statista.com/chart/3246/how-chinese-new-year-compares-with-thanksgiving/)\n\n# **Objectives**\n\n* What works and what doesn't work with this chart? \n* How can you make it better?","homepage":"https://data.world/makeovermonday/2019w6","resources":[{"name":"chinese_new_year_vs_thanksgiving","schema":{"fields":[{"name":"category","title":"Category","type":"string","rdfType":"http://www.w3.org/2001/XMLSchema#string","dwSourceId":"category"},{"name":"amount","title":"Amount","type":"integer","rdfType":"http://www.w3.org/2001/XMLSchema#integer","dwSourceId":"amount"},{"name":"country","title":"Country","type":"string","rdfType":"http://www.w3.org/2001/XMLSchema#string","dwSourceId":"country"},{"name":"unit","title":"Unit","type":"string","rdfType":"http://www.w3.org/2001/XMLSchema#string","dwSourceId":"unit"}]},"path":"data/chinese_new_year_vs_thanksgiving.csv","format":"csv"},{"name":"original/Chinese New Year vs Thanksgiving.xlsx","path":"original/Chinese New Year vs Thanksgiving.xlsx","format":"xlsx","mediatype":"application/vnd.openxmlformats-officedocument.spreadsheetml.sheet","bytes":10411}],"keywords":["chinese new year","consumer spending","thanksgiving","retail"]}